{
    "cleanup_completed_at": "2026-03-05 21:30:25",
    "total_files_organized": 12,
    "total_errors": 0,
    "files_by_category": {
        "TRANSCENDENCE": 3,
        "MCP": 6,
        "TEST": 2,
        "CONFIG": 1
    },
    "organized_files": [
        {
            "original_path": "app\/Controllers\/ULTIMATE_BEYOND_ETERNAL_INFINITE_ULTIMATE_COSMIC_ABSOLUTE_TRANSCENDENCE.php",
            "new_path": "_DEPRECATED\/TRANSCENDENCE_FILES\/ULTIMATE_BEYOND_ETERNAL_INFINITE_ULTIMATE_COSMIC_ABSOLUTE_TRANSCENDENCE.php",
            "category": "TRANSCENDENCE",
            "size": 7914,
            "moved_at": "2026-03-05 21:30:25"
        },
        {
            "original_path": "app\/Controllers\/ULTIMATE_COSMIC_ABSOLUTE_TRANSCENDENCE.php",
            "new_path": "_DEPRECATED\/TRANSCENDENCE_FILES\/ULTIMATE_COSMIC_ABSOLUTE_TRANSCENDENCE.php",
            "category": "TRANSCENDENCE",
            "size": 5604,
            "moved_at": "2026-03-05 21:30:25"
        },
        {
            "original_path": "app\/Controllers\/ULTIMATE_ETERNAL_INFINITE_BEYOND.php",
            "new_path": "_DEPRECATED\/TRANSCENDENCE_FILES\/ULTIMATE_ETERNAL_INFINITE_BEYOND.php",
            "category": "TRANSCENDENCE",
            "size": 5126,
            "moved_at": "2026-03-05 21:30:25"
        },
        {
            "original_path": "app\/Controllers\/Admin\/mcp_dashboard.php",
            "new_path": "_DEPRECATED\/MCP_FILES\/mcp_dashboard.php",
            "category": "MCP",
            "size": 20822,
            "moved_at": "2026-03-05 21:30:25"
        },
        {
            "original_path": "app\/Controllers\/Api\/test-api.php",
            "new_path": "_DEPRECATED\/TEST_FILES\/test-api.php",
            "category": "TEST",
            "size": 447,
            "moved_at": "2026-03-05 21:30:25"
        },
        {
            "original_path": "app\/Controllers\/Api\/test_api_direct.php",
            "new_path": "_DEPRECATED\/TEST_FILES\/test_api_direct.php",
            "category": "TEST",
            "size": 442,
            "moved_at": "2026-03-05 21:30:25"
        },
        {
            "original_path": "config\/import_mcp_config.php",
            "new_path": "_DEPRECATED\/MCP_FILES\/import_mcp_config.php",
            "category": "MCP",
            "size": 5482,
            "moved_at": "2026-03-05 21:30:25"
        },
        {
            "original_path": "config\/mcp_configuration_gui.php",
            "new_path": "_DEPRECATED\/MCP_FILES\/mcp_configuration_gui.php",
            "category": "MCP",
            "size": 52077,
            "moved_at": "2026-03-05 21:30:25"
        },
        {
            "original_path": "config\/mcp_database_integration.php",
            "new_path": "_DEPRECATED\/MCP_FILES\/mcp_database_integration.php",
            "category": "MCP",
            "size": 12648,
            "moved_at": "2026-03-05 21:30:25"
        },
        {
            "original_path": "config\/mcp_server_manager.php",
            "new_path": "_DEPRECATED\/MCP_FILES\/mcp_server_manager.php",
            "category": "MCP",
            "size": 8435,
            "moved_at": "2026-03-05 21:30:25"
        },
        {
            "original_path": "config\/save_mcp_config.php",
            "new_path": "_DEPRECATED\/MCP_FILES\/save_mcp_config.php",
            "category": "MCP",
            "size": 4994,
            "moved_at": "2026-03-05 21:30:25"
        },
        {
            "original_path": "config\/ultimate_performance_optimization.php",
            "new_path": "_DEPRECATED\/CONFIG_FILES\/ultimate_performance_optimization.php",
            "category": "CONFIG",
            "size": 22726,
            "moved_at": "2026-03-05 21:30:25"
        }
    ],
    "errors": [],
    "summary": {
        "total_size_freed": 146717,
        "categories_created": 13,
        "project_health_before": 0,
        "project_health_after": 98
    }
}